opni_nats/__init__.py
opni_nats/nats_wrapper.py
opni_nats-0.0.0.4.dist-info/LICENSE
opni_nats-0.0.0.4.dist-info/METADATA
opni_nats-0.0.0.4.dist-info/WHEEL
opni_nats-0.0.0.4.dist-info/top_level.txt
opni_nats-0.0.0.4.dist-info/RECORD
