Metadata-Version: 2.1
Name: opni-nats
Version: 0.0.0.4
Summary: A NATS helper used by Rancher Opni
Home-page: https://github.com/rancher/opni-nats-wrapper
Author: Rancher Labs
Author-email: sanjay.nadhavajhala@suse.com
License: UNKNOWN
Project-URL: Bug Tracker, https://github.com/rancher/opni-nats-wrapper/issues
Platform: UNKNOWN
Classifier: Programming Language :: Python :: 3
Classifier: License :: OSI Approved :: Apache Software License
Classifier: Operating System :: OS Independent
Requires-Python: >=3.6
License-File: LICENSE
Requires-Dist: asyncio-nats-client (>=0.9.0)
Requires-Dist: nkeys
